LICENSE
MANIFEST.in
README.md
pyproject.toml
setup.py
RLRAudioPropagationPkg/headers/RLRAudioPropagation.h
RLRAudioPropagationPkg/libs/linux/x64/libRLRAudioPropagation.so
rlr_audio_propagation/__init__.py
rlr_audio_propagation/core.py
rlr_audio_propagation.egg-info/PKG-INFO
rlr_audio_propagation.egg-info/SOURCES.txt
rlr_audio_propagation.egg-info/dependency_links.txt
rlr_audio_propagation.egg-info/not-zip-safe
rlr_audio_propagation.egg-info/requires.txt
rlr_audio_propagation.egg-info/top_level.txt
src/rlr_audio_bindings.cpp
tests/test_foa.py