Metadata-Version: 2.4
Name: rlr_audio_propagation
Version: 0.0.1
Summary: Python bindings for RLRAudioPropagation
License: Attribution-NonCommercial 4.0 International
License-File: LICENSE
Requires-Dist: numpy
Provides-Extra: test
Requires-Dist: trimesh; extra == "test"
Requires-Dist: pytest; extra == "test"
Dynamic: description
Dynamic: description-content-type
Dynamic: license
Dynamic: license-file
Dynamic: provides-extra
Dynamic: requires-dist
Dynamic: summary
